{
  "contract_version": "2026-06-06.1",
  "endpoint_summary": {
    "by_kind": {
      "data-artifact": 1,
      "docs": 3,
      "repo-registry": 1,
      "source-repo": 1,
      "website": 1
    },
    "by_layer": {
      "data-provider": 1,
      "docs-provider": 6
    },
    "by_publication_state": {
      "monitored": 7
    },
    "by_status": {
      "unknown": 7
    },
    "endpoint_count": 7,
    "monitored_count": 7,
    "pool_eligible_count": 0
  },
  "generated_at": "1970-01-01T00:00:00.000Z",
  "provider": {
    "authority": "provider-claimed",
    "docs_url": "https://docs.gittensor.io/",
    "id": "gittensor",
    "kind": "subnet-team",
    "name": "Gittensor",
    "notes": "Seed provider entry for the Gittensor SN74 pilot.",
    "schema_version": 1,
    "website_url": "https://gittensor.io"
  },
  "schema_version": 1
}
